iguanas/__init__.py
iguanas/correlation_reduction/__init__.py
iguanas/correlation_reduction/agglomerative_clustering_reducer.py
iguanas/exceptions/__init__.py
iguanas/exceptions/exceptions.py
iguanas/metrics/__init__.py
iguanas/metrics/classification.py
iguanas/metrics/pairwise.py
iguanas/metrics/unsupervised.py
iguanas/pipeline/__init__.py
iguanas/pipeline/_base_pipeline.py
iguanas/pipeline/class_accessor.py
iguanas/pipeline/linear_pipeline.py
iguanas/pipeline/parallel_pipeline.py
iguanas/rbs/__init__.py
iguanas/rbs/rbs_optimiser.py
iguanas/rbs/rbs_pipeline.py
iguanas/rule_application/__init__.py
iguanas/rule_application/rule_applier.py
iguanas/rule_generation/__init__.py
iguanas/rule_generation/_base_generator.py
iguanas/rule_generation/rule_generator_dt.py
iguanas/rule_generation/rule_generator_dt_spark.py
iguanas/rule_generation/rule_generator_opt.py
iguanas/rule_optimisation/__init__.py
iguanas/rule_optimisation/_base_optimiser.py
iguanas/rule_optimisation/bayesian_optimiser.py
iguanas/rule_optimisation/direct_search_optimiser.py
iguanas/rule_scoring/__init__.py
iguanas/rule_scoring/rule_score_scalers.py
iguanas/rule_scoring/rule_scorer.py
iguanas/rule_scoring/rule_scoring_methods.py
iguanas/rule_selection/__init__.py
iguanas/rule_selection/_base_filter.py
iguanas/rule_selection/bayes_search_cv.py
iguanas/rule_selection/correlated_filter.py
iguanas/rule_selection/greedy_filter.py
iguanas/rule_selection/simple_filter.py
iguanas/rules/__init__.py
iguanas/rules/_convert_rule_dicts_to_rule_lambdas.py
iguanas/rules/_convert_rule_dicts_to_rule_strings.py
iguanas/rules/_convert_rule_lambdas_to_rule_strings.py
iguanas/rules/_convert_rule_strings_to_rule_dicts.py
iguanas/rules/_get_rule_attributes.py
iguanas/rules/convert_processed_conditions_to_general.py
iguanas/rules/rules.py
iguanas/space/__init__.py
iguanas/space/spaces.py
iguanas/utils/__init__.py
iguanas/utils/types.py
iguanas/utils/typing.py
iguanas/utils/utils.py
iguanas/warnings/__init__.py
iguanas-0.1.4.dist-info/LICENSE
iguanas-0.1.4.dist-info/METADATA
iguanas-0.1.4.dist-info/WHEEL
iguanas-0.1.4.dist-info/top_level.txt
iguanas-0.1.4.dist-info/RECORD
